fake_api_server/__init__.py
fake_api_server/__main__.py
fake_api_server/__pkg_info__.py
fake_api_server/_utils/__init__.py
fake_api_server/_utils/api_client.py
fake_api_server/_utils/file/__init__.py
fake_api_server/_utils/file/operation.py
fake_api_server/_utils/importing.py
fake_api_server/_utils/random.py
fake_api_server/_utils/uri_protocol.py
fake_api_server/command/__init__.py
fake_api_server/command/_base/__init__.py
fake_api_server/command/_base/component.py
fake_api_server/command/_base/options.py
fake_api_server/command/_base/process.py
fake_api_server/command/_common/__init__.py
fake_api_server/command/_common/component.py
fake_api_server/command/_parser.py
fake_api_server/command/component.py
fake_api_server/command/options.py
fake_api_server/command/process.py
fake_api_server/command/rest_server/__init__.py
fake_api_server/command/rest_server/add/__init__.py
fake_api_server/command/rest_server/add/component.py
fake_api_server/command/rest_server/add/options.py
fake_api_server/command/rest_server/add/process.py
fake_api_server/command/rest_server/check/__init__.py
fake_api_server/command/rest_server/check/component.py
fake_api_server/command/rest_server/check/options.py
fake_api_server/command/rest_server/check/process.py
fake_api_server/command/rest_server/component.py
fake_api_server/command/rest_server/get/__init__.py
fake_api_server/command/rest_server/get/component.py
fake_api_server/command/rest_server/get/options.py
fake_api_server/command/rest_server/get/process.py
fake_api_server/command/rest_server/option.py
fake_api_server/command/rest_server/process.py
fake_api_server/command/rest_server/pull/__init__.py
fake_api_server/command/rest_server/pull/component.py
fake_api_server/command/rest_server/pull/options.py
fake_api_server/command/rest_server/pull/process.py
fake_api_server/command/rest_server/run/__init__.py
fake_api_server/command/rest_server/run/component.py
fake_api_server/command/rest_server/run/options.py
fake_api_server-0.4.2.dist-info/LICENSE
fake_api_server-0.4.2.dist-info/METADATA
fake_api_server-0.4.2.dist-info/WHEEL
fake_api_server-0.4.2.dist-info/entry_points.txt
fake_api_server-0.4.2.dist-info/RECORD
