Metadata-Version: 2.3
Name: fake-api-server
Version: 0.4.2
Summary: 🕸🤖👺 A Python tool to fake API server, e.g., RESTful API server, easily and humanly without any coding.
License: MIT License
Keywords: mock,API,mock server,mock API server,web,server
Author: Liu, Bryant
Author-email: chi10211201@cycu.org.tw
Requires-Python: >=3.9,<3.13
Classifier: Development Status :: 3 - Alpha
Classifier: Intended Audience :: Developers
Classifier: Topic :: Internet
Classifier: Topic :: Utilities
Classifier: Topic :: Software Development :: Libraries :: Python Modules
Classifier: Topic :: Software Development :: Testing :: Mocking
Classifier: Topic :: Internet :: WWW/HTTP
Classifier: Topic :: Internet :: WWW/HTTP :: HTTP Servers
Classifier: Topic :: Internet :: WWW/HTTP :: Dynamic Content
Classifier: License :: OSI Approved :: MIT License
Classifier: Operating System :: OS Independent
Classifier: Environment :: Console
Classifier: Programming Language :: Python :: 3
Classifier: Programming Language :: Python :: 3.9
Classifier: Programming Language :: Python :: 3.10
Classifier: Programming Language :: Python :: 3.11
Classifier: Programming Language :: Python :: 3.12
Classifier: Programming Language :: Python :: 3.13
Provides-Extra: all
Provides-Extra: fastapi
Provides-Extra: flask
Provides-Extra: mini
Requires-Dist: Flask (>=3.0.2) ; extra == "all"
Requires-Dist: Flask (>=3.0.2) ; extra == "flask"
Requires-Dist: PyYAML (>=6.0)
Requires-Dist: PyYAML (>=6.0) ; extra == "all"
Requires-Dist: PyYAML (>=6.0) ; extra == "fastapi"
Requires-Dist: PyYAML (>=6.0) ; extra == "flask"
Requires-Dist: PyYAML (>=6.0) ; extra == "mini"
Requires-Dist: fastapi (>=0.110,<0.116) ; extra == "all"
Requires-Dist: fastapi (>=0.110,<0.116) ; extra == "fastapi"
Requires-Dist: gunicorn (>=21.2,<24.0) ; extra == "all"
Requires-Dist: gunicorn (>=21.2,<24.0) ; extra == "flask"
Requires-Dist: urllib3 (>=2.3.0,<3.0.0)
Requires-Dist: uvicorn (>=0.29,<0.34) ; extra == "all"
Requires-Dist: uvicorn (>=0.29,<0.34) ; extra == "fastapi"
Project-URL: Changelog, https://chisanan232.github.io/PyFake-API-Server/latest/release_note/
Project-URL: Documentation, https://chisanan232.github.io/PyFake-API-Server/stable/
Project-URL: Homepage, https://github.com/Chisanan232/PyFake-API-Server
Project-URL: Project Management, https://app.clickup.com/9018752317/v/f/90183126979/90182605225
Project-URL: Repository, https://github.com/Chisanan232/PyFake-API-Server
